clicarriots/__init__.py
clicarriots/api.py
clicarriots/client.py
clicarriots-0.2.0.dist-info/METADATA
clicarriots-0.2.0.dist-info/RECORD
clicarriots-0.2.0.dist-info/WHEEL
clicarriots-0.2.0.dist-info/top_level.txt
