Metadata-Version: 2.1
Name: clicarriots
Version: 0.2.0
Summary: The unofficial simple client for carriots platform (in progress) (python 2.x/3.x)
Home-page: https://github.com/sdeancos/clicarriots
Author: Samuel de Ancos
Author-email: sdeancos@gmail.com
License: UNKNOWN
Download-URL: https://github.com/sdeancos/clicarriots/tarball/0.2.0
Keywords: carriots,iot,internet of things
Platform: UNKNOWN
